{
  "export_timestamp": "2025-08-05T17:38:18.240924",
  "performance_metrics": {
    "performance": {
      "avg_response_time": 7.82,
      "max_response_time": 16.73,
      "min_response_time": 0.0,
      "success_rate": 100.0,
      "rag_usage_rate": 50.0
    },
    "usage": {
      "total_queries": 4,
      "successful_queries": 4,
      "uptime_hours": 0.0,
      "popular_query_types": [
        [
          "constitutional",
          2
        ],
        [
          "politeness",
          2
        ]
      ],
      "frequent_errors": []
    },
    "quality": {
      "avg_satisfaction": 0,
      "total_feedback": 0
    },
    "alerts": [
      "Temps de r\u00e9ponse \u00e9lev\u00e9: 7.82s",
      "Utilisation RAG faible: 50.0%"
    ]
  },
  "raw_metrics": {
    "response_times": [
      {
        "timestamp": "2025-08-05 17:38:03.713535",
        "response_time": 16.734848976135254,
        "query": "Droits fondamentaux"
      },
      {
        "timestamp": "2025-08-05 17:38:18.240396",
        "response_time": 14.526657104492188,
        "query": "Pouvoir ex\u00e9cutif"
      },
      {
        "timestamp": "2025-08-05 17:38:18.240610",
        "response_time": 1.5020370483398438e-05,
        "query": "Bonjour"
      },
      {
        "timestamp": "2025-08-05 17:38:18.240713",
        "response_time": 6.9141387939453125e-06,
        "query": "Merci"
      }
    ],
    "query_types": {
      "constitutional": 2,
      "politeness": 2
    },
    "error_counts": {},
    "rag_usage": [
      {
        "timestamp": "2025-08-05 17:38:03.713535",
        "used_rag": true,
        "confidence": 0.8
      },
      {
        "timestamp": "2025-08-05 17:38:18.240396",
        "used_rag": true,
        "confidence": 0.8
      },
      {
        "timestamp": "2025-08-05 17:38:18.240610",
        "used_rag": false,
        "confidence": 1.0
      },
      {
        "timestamp": "2025-08-05 17:38:18.240713",
        "used_rag": false,
        "confidence": 1.0
      }
    ],
    "user_satisfaction": []
  }
}